CHANGES.txt
setup.py
topp/__init__.py
topp.featurelets.egg-info/PKG-INFO
topp.featurelets.egg-info/SOURCES.txt
topp.featurelets.egg-info/dependency_links.txt
topp.featurelets.egg-info/entry_points.txt
topp.featurelets.egg-info/namespace_packages.txt
topp.featurelets.egg-info/not-zip-safe
topp.featurelets.egg-info/requires.txt
topp.featurelets.egg-info/top_level.txt
topp/featurelets/README.txt
topp/featurelets/__init__.py
topp/featurelets/base.py
topp/featurelets/config.py
topp/featurelets/configure.zcml
topp/featurelets/interfaces.py
topp/featurelets/menusupporter.py
topp/featurelets/registry.py
topp/featurelets/supporter.py
topp/featurelets/tests/__init__.py
topp/featurelets/tests/base.py
topp/featurelets/tests/dummy.py
topp/featurelets/tests/test_config.py
topp/featurelets/tests/test_content.py
topp/featurelets/tests/test_objects.py
topp/featurelets/tests/utils.py