Metadata-Version: 1.0
Name: topp.featurelets
Version: 0.3.0
Summary: Base support for plone featurelets (i.e. feature plugins)
Home-page: https://svn.openplans.org/svn/topp.featurelets/
Author: Rob Miller
Author-email: robm@openplans.org
License: GPL
Keywords: featurelets openplans plone topp
Platform: UNKNOWN
Classifier: Framework :: Plone
Classifier: Framework :: Zope2
Classifier: License :: OSI Approved :: GNU General Public License (GPL)
Classifier: Programming Language :: Python :: 2
